AUTHORS.rst
CHANGES.rst
LICENSE.txt
MANIFEST.in
README.rst
setup.py
django_transaction_hooks.egg-info/PKG-INFO
django_transaction_hooks.egg-info/SOURCES.txt
django_transaction_hooks.egg-info/dependency_links.txt
django_transaction_hooks.egg-info/not-zip-safe
django_transaction_hooks.egg-info/requires.txt
django_transaction_hooks.egg-info/top_level.txt
transaction_hooks/__init__.py
transaction_hooks/mixin.py
transaction_hooks/backends/__init__.py
transaction_hooks/backends/mysql/__init__.py
transaction_hooks/backends/mysql/base.py
transaction_hooks/backends/postgis/__init__.py
transaction_hooks/backends/postgis/base.py
transaction_hooks/backends/postgresql_psycopg2/__init__.py
transaction_hooks/backends/postgresql_psycopg2/base.py
transaction_hooks/backends/sqlite3/__init__.py
transaction_hooks/backends/sqlite3/base.py
transaction_hooks/test/__init__.py
transaction_hooks/test/models.py
transaction_hooks/test/settings.py
transaction_hooks/test/settings_mysql.py
transaction_hooks/test/settings_pg.py
transaction_hooks/test/settings_postgis.py
transaction_hooks/test/settings_sqlite3.py
transaction_hooks/test/test_basic.py