Metadata-Version: 1.1
Name: django-transaction-hooks
Version: 0.2
Summary: Django database backends that permit registering post-transaction-commit hooks
Home-page: https://github.com/carljm/django-transaction-hooks/
Author: Carl Meyer
Author-email: carl@oddbird.net
License: UNKNOWN
Platform: UNKNOWN
Classifier: Development Status :: 3 - Alpha
Classifier: Environment :: Web Environment
Classifier: Intended Audience :: Developers
Classifier: License :: OSI Approved :: BSD License
Classifier: Operating System :: OS Independent
Classifier: Programming Language :: Python
Classifier: Programming Language :: Python :: 2.6
Classifier: Programming Language :: Python :: 2.7
Classifier: Programming Language :: Python :: 3
Classifier: Programming Language :: Python :: 3.2
Classifier: Programming Language :: Python :: 3.3
Classifier: Framework :: Django
